attribute_dict/__init__.py
tests/__init__.py
tests/test_attribute_dict.py
tests/utils.py
attribute_dict-1.0.0.dist-info/LICENSE
attribute_dict-1.0.0.dist-info/METADATA
attribute_dict-1.0.0.dist-info/WHEEL
attribute_dict-1.0.0.dist-info/top_level.txt
attribute_dict-1.0.0.dist-info/RECORD
